frist/__init__.py
frist/_age.py
frist/_cal.py
frist/_cal_policy.py
frist/_constants.py
frist/_frist.py
frist/py.typed
frist-0.11.0.dist-info/METADATA
frist-0.11.0.dist-info/WHEEL
frist-0.11.0.dist-info/top_level.txt
frist-0.11.0.dist-info/RECORD
