Metadata-Version: 2.4
Name: frist
Version: 0.11.0
Summary: Calendar-based time window filtering, age calculations, and business logic for dates and times.
Author-email: Chuck Hucker <chuck@hucker.com>
Project-URL: Homepage, https://github.com/hucker/frist
Project-URL: Repository, https://github.com/hucker/frist
Project-URL: Issues, https://github.com/hucker/frist/issues
Classifier: Programming Language :: Python :: 3
Classifier: License :: OSI Approved :: MIT License
Classifier: Operating System :: OS Independent
Requires-Python: >=3.10
Provides-Extra: dev
Requires-Dist: pytest; extra == "dev"
Requires-Dist: pytest-cov; extra == "dev"
